.gitignore
.pre-commit-config.yaml
.pylintrc
AUTHORS.md
CHANGELOG.md
LICENSE
MANIFEST.in
NOTICE
README.md
pyproject.toml
setup.cfg
setup.py
sonar-project.properties
.github/workflows/pandora_plugin_mccnn.yml
data_samples/desert_census.png
data_samples/desert_img.png
data_samples/desert_mccnn_fast_data_fusion_contest.png
data_samples/desert_mccnn_fast_middlebury.png
data_samples/mountain_census.png
data_samples/mountain_img.png
data_samples/mountain_mccnn_fast_data_fusion_contest.png
data_samples/mountain_mccnn_fast_middlebury.png
doc/Makefile
doc/make.bat
doc/source/conf.py
doc/source/getting_started.rst
doc/source/index.rst
doc/source/_static/css/my_custom.css
pandora_plugin_mc_cnn/__init__.py
pandora_plugin_mc_cnn/plugin_mc_cnn.py
pandora_plugin_mccnn.egg-info/PKG-INFO
pandora_plugin_mccnn.egg-info/SOURCES.txt
pandora_plugin_mccnn.egg-info/dependency_links.txt
pandora_plugin_mccnn.egg-info/entry_points.txt
pandora_plugin_mccnn.egg-info/requires.txt
pandora_plugin_mccnn.egg-info/top_level.txt
tests/conftest.py
tests/test_cfg_mccnn_fast.json
tests/test_cfg_mccnn_fast_default_values.json
tests/test_cfg_mccnn_fast_multiband.json
tests/test_check_configuration.py
tests/test_plugin.py
tests/image/__init__.py
tests/image/disp_left.tif
tests/image/disp_right.tif
tests/image/left_img.png
tests/image/left_rgb.tif
tests/image/right_img.png
tests/image/right_rgb.tif
tests/weights/mc_cnn_fast_mb_weights.pt