Metadata-Version: 2.4
Name: pandora_plugin_mccnn
Version: 1.3.5
Summary: Pandora plugin to create the cost volume with the neural network mc-cnn
Home-page: https://github.com/CNES/Pandora_plugin_mccnn
Author: CNES
Author-email: myriam.cournet@cnes.fr
License: Apache License 2.0
Requires-Python: >=3.8
License-File: LICENSE
Requires-Dist: numpy
Requires-Dist: MCCNN>=1.2.3
Requires-Dist: pandora==1.7.*
Requires-Dist: xarray
Requires-Dist: json-checker
Provides-Extra: dev
Requires-Dist: pytest; extra == "dev"
Requires-Dist: pytest-cov; extra == "dev"
Requires-Dist: pylint; extra == "dev"
Requires-Dist: pre-commit; extra == "dev"
Requires-Dist: black; extra == "dev"
Provides-Extra: docs
Requires-Dist: sphinx; extra == "docs"
Requires-Dist: sphinx_rtd_theme; extra == "docs"
Requires-Dist: sphinx_autoapi; extra == "docs"
Dynamic: description
Dynamic: license-file
